oauth2_wordpress/__about__.py
oauth2_wordpress/__init__.py
oauth2_wordpress/wp_oauth.py
edx_oauth2_wordpress_backend-1.0.8.dist-info/LICENSE.txt
edx_oauth2_wordpress_backend-1.0.8.dist-info/METADATA
edx_oauth2_wordpress_backend-1.0.8.dist-info/WHEEL
edx_oauth2_wordpress_backend-1.0.8.dist-info/top_level.txt
edx_oauth2_wordpress_backend-1.0.8.dist-info/RECORD
