Metadata-Version: 2.1
Name: edx-oauth2-wordpress-backend
Version: 1.0.8
Summary: An Open edX Python Social Auth backend for Wordpress
Home-page: https://github.com/StepwiseMath/edx-oauth2-wordpress-backend
Author: Lawrence McDaniel, lpm0073@gmail.com
Author-email: Lawrence McDaniel <lpm0073@gmail.com>
Project-URL: Homepage, https://github.com/lpm0073/edx-oauth2-wordpress-backend
Project-URL: Bug Tracker, https://github.com/lpm0073/edx-oauth2-wordpress-backend/issues
Keywords: Open edX,oauth,Wordpress
Classifier: Programming Language :: Python :: 3
Classifier: License :: OSI Approved :: MIT License
Classifier: Operating System :: OS Independent
Requires-Python: >=3.7
License-File: LICENSE.txt
Requires-Dist: social-auth-core ==4.3.0
Requires-Dist: social-auth-app-django ==5.0.0
